Topsis/__init__.py
Topsis/mymodule_102117021.py
Topsis_Aaditya_102117021-0.0.4.dist-info/METADATA
Topsis_Aaditya_102117021-0.0.4.dist-info/WHEEL
Topsis_Aaditya_102117021-0.0.4.dist-info/top_level.txt
Topsis_Aaditya_102117021-0.0.4.dist-info/RECORD
