Metadata-Version: 2.1
Name: Topsis-Aaditya-102117021
Version: 0.0.4
Summary: Implementing TOPSIS
Author: intrinsicvardhan (Aaditya Vardhan)
Author-email: intrinsicvardhan@gmail.com
Keywords: topsis,decision-analysis,similarity
Classifier: Development Status :: 1 - Planning
Classifier: Intended Audience :: Developers
Classifier: Programming Language :: Python :: 3
Classifier: Operating System :: Unix
Classifier: Operating System :: MacOS :: MacOS X
Classifier: Operating System :: Microsoft :: Windows
Requires-Dist: pandas
Requires-Dist: numpy
